README.rst
setup.py
steno3d/__init__.py
steno3d/base.py
steno3d/client.py
steno3d/data.py
steno3d/line.py
steno3d/options.py
steno3d/parsers.py
steno3d/point.py
steno3d/project.py
steno3d/props.py
steno3d/query.py
steno3d/surface.py
steno3d/texture.py
steno3d/user.py
steno3d/vector.py
steno3d/volume.py
steno3d.egg-info/PKG-INFO
steno3d.egg-info/SOURCES.txt
steno3d.egg-info/dependency_links.txt
steno3d.egg-info/requires.txt
steno3d.egg-info/top_level.txt
steno3d/examples/__init__.py
steno3d/examples/airports.py
steno3d/examples/base.py
steno3d/examples/brain.py
steno3d/examples/misc.py
steno3d/examples/rocket.py
steno3d/examples/teapot.py
steno3d/examples/topography.py
steno3d/examples/tsyganenko.py
steno3d/examples/wolfpass.py